[
  {
    "icon": "Blog",
    "name": "博客",
    "link": "https://notes.wudetian.top/notes/directory.html"
  },
  {
    "icon": "Compass",
    "name": "起始页",
    "link": "https://nav.imsyy.top/"
  },
  {
    "icon": "Fire",
    "name": "今日热榜",
    "link": "https://hot.imsyy.top/"
  },
  {
    "icon": "Book",
    "name": "MUI模板",
    "link": "http://mui.wudetian.top/"
  },
  {
    "icon": "Cloud",
    "name": "DIY仓库",
    "link": "https://wudetian.top/"
  },
  {
    "icon": "CompactDisc",
    "name": "待开发...",
    "link": "https://wudetian.top/"
  },
  {
    "icon": "CompactDisc",
    "name": "待开发...",
    "link": "https://wudetian.top/"
  }
]